[
  {
    "id": 0,
    "name": "Sample title - big data solutions",
    "image": "images/s1.jpg",
    "url": "#",
    "items": [
      {
        "name": "Web design<strong>WEB</strong>",
        "url": "#"
      },
      {
        "name": "Wordpress",
        "url": "#"
      },
      {
        "name": "Logotype",
        "url": "#"
      }
    ]
  },
  {
    "id": 1,
    "name": "Pure ipsum - development services for people",
    "image": "images/s1.jpg",
    "url": "#",
    "items": [
      {
        "name": "Web design",
        "url": "#"
      },
      {
        "name": "Wordpress",
        "url": "#"
      }
    ]
  }
]
